qtinter/__init__.py
qtinter/_base_events.py
qtinter/_contexts.py
qtinter/_helpers.py
qtinter/_ki.py
qtinter/_modal.py
qtinter/_proactor_events.py
qtinter/_selectable.py
qtinter/_selector_events.py
qtinter/_signals.py
qtinter/_slots.py
qtinter/_tasks.py
qtinter/_unix_events.py
qtinter/_windows_events.py
qtinter/bindings.py
qtinter-0.11.0.dist-info/LICENSE
qtinter-0.11.0.dist-info/METADATA
qtinter-0.11.0.dist-info/WHEEL
qtinter-0.11.0.dist-info/top_level.txt
qtinter-0.11.0.dist-info/RECORD
